ClusterMonitor/__init__.py
ClusterMonitor/cpu_ram_log.py
ClusterMonitor/visualize_log.py
ClusterMonitor-0.0.7.data/scripts/cpu_ram_log
ClusterMonitor-0.0.7.data/scripts/visualize_log
ClusterMonitor-0.0.7.dist-info/METADATA
ClusterMonitor-0.0.7.dist-info/WHEEL
ClusterMonitor-0.0.7.dist-info/top_level.txt
ClusterMonitor-0.0.7.dist-info/RECORD
