Metadata-Version: 2.1
Name: ClusterMonitor
Version: 0.0.7
Summary: Simple script which can be used to monitor and log CPU and RAM usage of submitted cluster jobs
Home-page: UNKNOWN
Author: nickhir
License: UNKNOWN
Keywords: python,cluster,monitor,CPU,RAM,usage,SLURM
Platform: UNKNOWN
Classifier: Operating System :: Unix
Requires-Dist: matplotlib
